rqs.py
rqs-0.4.0.dist-info/LICENSE
rqs-0.4.0.dist-info/METADATA
rqs-0.4.0.dist-info/WHEEL
rqs-0.4.0.dist-info/entry_points.txt
rqs-0.4.0.dist-info/top_level.txt
rqs-0.4.0.dist-info/RECORD
