Metadata-Version: 2.2
Name: rqs
Version: 0.4.0
Summary: A handy tool to manage your credentials or frequent used commands.
Author-email: tvytlx <tvytlx@gmail.com>
License: MIT
Project-URL: Homepage, https://github.com/tvytlx/rqs
Classifier: License :: OSI Approved :: MIT License
Classifier: Programming Language :: Python
Classifier: Programming Language :: Python :: 3
Classifier: Programming Language :: Python :: 3.6
Classifier: Programming Language :: Python :: Implementation :: CPython
Classifier: Programming Language :: Python :: Implementation :: PyPy
Requires-Python: >=3.6.0
License-File: LICENSE
Requires-Dist: click
Requires-Dist: simplekv
Requires-Dist: crayons
